MANIFEST.in
README.md
requirements.txt
setup.py
django_admin_app_sidebar/__init__.py
django_admin_app_sidebar/admin.py
django_admin_app_sidebar/apps.py
django_admin_app_sidebar/models.py
django_admin_app_sidebar/portlets.py
django_admin_app_sidebar/tests.py
django_admin_app_sidebar/views.py
django_admin_app_sidebar.egg-info/PKG-INFO
django_admin_app_sidebar.egg-info/SOURCES.txt
django_admin_app_sidebar.egg-info/dependency_links.txt
django_admin_app_sidebar.egg-info/not-zip-safe
django_admin_app_sidebar.egg-info/requires.txt
django_admin_app_sidebar.egg-info/top_level.txt
django_admin_app_sidebar/migrations/__init__.py
django_admin_app_sidebar/static/django-admin-app-sidebar/css/django-admin-app-sidebar.css
django_admin_app_sidebar/static/django-admin-app-sidebar/css/fix-changeform-problem.css
django_admin_app_sidebar/static/django-admin-app-sidebar/js/fix-changelist-problem.js
django_admin_app_sidebar/templates/admin/app_index.html
django_admin_app_sidebar/templates/admin/change_form.html
django_admin_app_sidebar/templates/admin/change_list.html
django_admin_app_sidebar/templates/django-admin-app-sidebar/sidebar-navigation.html
django_admin_app_sidebar/templates/django-admin-app-sidebar/sidebar-portlets.html
django_admin_app_sidebar/templatetags/__init__.py
django_admin_app_sidebar/templatetags/django_admin_app_sidebar.py