Metadata-Version: 2.1
Name: django-admin-app-sidebar
Version: 0.1.0
Summary: A django application that add portlets in right sidebar at app level.
Home-page: UNKNOWN
Author: zencore
Author-email: dobetter@zencore.cn
License: MIT
Keywords: django admin extentions,django admin app sidebar
Platform: UNKNOWN
Classifier: Development Status :: 5 - Production/Stable
Classifier: Intended Audience :: Developers
Classifier: Topic :: Software Development :: Libraries :: Python Modules
Classifier: License :: OSI Approved :: MIT License
Classifier: Programming Language :: Python :: 3
Classifier: Programming Language :: Python :: 3 :: Only
